kirahhe/__init__.py
kirahhe/version.py
kirahhe-0.2.data/scripts/kirahhe
kirahhe-0.2.dist-info/METADATA
kirahhe-0.2.dist-info/RECORD
kirahhe-0.2.dist-info/WHEEL
kirahhe-0.2.dist-info/top_level.txt
