Metadata-Version: 2.1
Name: kirahhe
Version: 0.2
Summary: Startup process catcher
Home-page: https://github.com/kirillmakhonin/kirahhe
Author: Kirill Makhonin
Author-email: kirill@makhonin.biz
License: Apache v2
Platform: UNKNOWN
Classifier: Programming Language :: Python :: 3
Classifier: License :: OSI Approved :: MIT License
Classifier: Operating System :: POSIX :: Linux
Classifier: Topic :: Software Development :: Debuggers
Classifier: Topic :: System :: Monitoring
